gsbg/__init__.py
gsbg/google_scholar_badge_generator.py
gsbg/tests/__init__.py
gsbg/tests/gsbg.py
gsbg-0.1.3.dist-info/LICENSE
gsbg-0.1.3.dist-info/METADATA
gsbg-0.1.3.dist-info/WHEEL
gsbg-0.1.3.dist-info/top_level.txt
gsbg-0.1.3.dist-info/RECORD
