Metadata-Version: 2.1
Name: gsbg
Version: 0.1.3
Summary: A tool for Google Scholar citation badge generation.
Home-page: https://github.com/WenjieDu/Google_Scholar_Badge_Generator
Download-URL: https://github.com/WenjieDu/Google_Scholar_Badge_Generator/archive/main.zip
Author: Wenjie Du
Author-email: wenjay.du@gmail.com
License: GPL-3.0
Keywords: Google Scholar,citation,citation number,shields.io,badge,svg,generating
Classifier: Development Status :: 4 - Beta
Classifier: Intended Audience :: Developers
Classifier: Intended Audience :: Education
Classifier: Intended Audience :: Science/Research
Classifier: License :: OSI Approved :: GNU General Public License v3 (GPLv3)
Classifier: Operating System :: OS Independent
Classifier: Programming Language :: Python :: 3
Requires-Python: >=3.5
License-File: LICENSE
Requires-Dist: beautifulsoup4
Requires-Dist: requests
